database/__init__.py
database/config.py
database/models/__init__.py
database/models/bot/__init__.py
database/models/bot/bot.py
database/models/bot/info/__init__.py
database/models/bot/info/gmeet.py
database/models/session.py
database/models/telegram_user.py
database/models/user.py
database/py.typed
main_database_models-0.6.0.dist-info/METADATA
main_database_models-0.6.0.dist-info/WHEEL
main_database_models-0.6.0.dist-info/RECORD
