Metadata-Version: 2.3
Name: main-database-models
Version: 0.6.0
Summary: 
Author: ycalk
Author-email: alosev752@gmail.com
Requires-Python: >=3.11
Classifier: Programming Language :: Python :: 3
Classifier: Programming Language :: Python :: 3.11
Classifier: Programming Language :: Python :: 3.12
Classifier: Programming Language :: Python :: 3.13
Requires-Dist: aerich (>=0.9.1,<0.10.0)
Requires-Dist: bot-shared-models (>=0.3.0,<0.4.0)
Requires-Dist: gmeet-shared-models (>=1.6.0,<1.7.0)
Requires-Dist: python-dotenv (>=1.1.1,<2.0.0)
Requires-Dist: session-shared-models (>=0.3.0,<0.4.0)
Requires-Dist: tortoise-orm[asyncpg] (>=0.25.1,<0.26.0)
Requires-Dist: uuid6 (>=2025.0.0,<2026.0.0)
